compose/__init__.py
compose/postgres.py
compose/py.typed
compose/sentry.py
nanodjango_compose-0.0.0.dev0.dist-info/METADATA
nanodjango_compose-0.0.0.dev0.dist-info/WHEEL
nanodjango_compose-0.0.0.dev0.dist-info/licenses/LICENSE.txt
nanodjango_compose-0.0.0.dev0.dist-info/RECORD
