Metadata-Version: 2.4
Name: nanodjango-compose
Version: 0.0.0.dev0
Summary: A library of plugins for configuring a production-ready Django site when you convert your nanodjango single page app.
Author-email: Stuart MacKay <smackay@flagstonesoftware.com>
License: MIT License
License-File: LICENSE.txt
Requires-Python: >=3.12
Requires-Dist: nanodjango>=0.11.2
